cdv
tests
