Metadata-Version: 2.4
Name: chik_dev_tools
Version: 1.2.14
Summary: Chik development commands
Home-page: https://github.com/Chik-Network
Author: Quexington
Author-email: m.hauff@chiknetwork.com
License: https://opensource.org/licenses/Apache-2.0
Project-URL: Bug Reports, https://github.com/Chik-Network/chik-dev-tools
Project-URL: Source, https://github.com/Chik-Network/chik-dev-tools
Classifier: Programming Language :: Python :: 3
Classifier: Programming Language :: Python :: 3.9
Classifier: Programming Language :: Python :: 3.10
Classifier: Programming Language :: Python :: 3.11
Classifier: License :: OSI Approved :: Apache Software License
Classifier: Topic :: Security :: Cryptography
License-File: LICENSE
Requires-Dist: packaging
Requires-Dist: pytest
Requires-Dist: pytest-asyncio
Requires-Dist: pytimeparse
Requires-Dist: anyio
Requires-Dist: chik-blockchain==2.5.4
Provides-Extra: dev
Requires-Dist: anyio; extra == "dev"
Requires-Dist: mypy; extra == "dev"
Requires-Dist: ruff>=0.8.1; extra == "dev"
Requires-Dist: types-aiofiles; extra == "dev"
Requires-Dist: types-click; extra == "dev"
Requires-Dist: types-cryptography; extra == "dev"
Requires-Dist: types-setuptools; extra == "dev"
Requires-Dist: types-pyyaml; extra == "dev"
Requires-Dist: types-setuptools; extra == "dev"
Requires-Dist: pre-commit; extra == "dev"
Dynamic: author
Dynamic: author-email
Dynamic: classifier
Dynamic: description
Dynamic: description-content-type
Dynamic: home-page
Dynamic: license
Dynamic: license-file
Dynamic: project-url
Dynamic: provides-extra
Dynamic: requires-dist
Dynamic: summary
